Metadata-Version: 1.0
Name: fizzaPythonUtility
Version: 0.0.3
Summary: Python utility
Home-page: UNKNOWN
Author: Fizza
Author-email: UNKNOWN
License: LICENSE.txt
Platform: UNKNOWN
